<?xml version="1.0" encoding="UTF-8"?>
<!-- Generated by JClic - https://projectestac.github.io/jclic -->
<manifest identifier="JClic-BE2A33" version="1.0" xmlns="http://www.imsproject.org/xsd/imscp_rootv1p1p2" xmlns:adlcp="http://www.adlnet.org/xsd/adlcp_rootv1p2" xmlns:xsi="http://www.w3.org/2001/XMLSchema-instance" xsi:schemaLocation= "http://www.imsproject.org/xsd/imscp_rootv1p1p2 imscp_rootv1p1p2.xsd http://www.imsglobal.org/xsd/imsmd_rootv1p2p1 imsmd_rootv1p2p1.xsd http://www.adlnet.org/xsd/adlcp_rootv1p2 adlcp_rootv1p2.xsd">
 <metadata> 
  <schema>ADL SCORM</schema>
  <schemaversion>1.2</schemaversion>
 </metadata> 
 <organizations default="JClic">  
  <organization identifier="JClic">  
   <title>actividad4</title>
   <item identifier="ITEM_JClic-BE2A33" identifierref="RES_JClic-BE2A33">
    <title>actividad4</title>
   </item>
  </organization>
 </organizations>
 <resources>
  <resource identifier="RES_JClic-BE2A33" type="webcontent" href="/index.html" adlcp:scormtype="sco"> 
   <file href="1200px-copyright.svg-resized.jpg"/>
   <file href="actividad4.jclic"/>
   <file href="actividad4.jclic.js"/>
   <file href="favicon.ico"/>
   <file href="historia-de-la-computadora-mouse-engelbart-e1558311514169.jpg"/>
   <file href="icon-192.png"/>
   <file href="icon-72.png"/>
   <file href="imagen-de-mohamed-hassan-en-pixabay-resized.jpg"/>
   <file href="imsmanifest.xml"/>
   <file href="index.html"/>
   <file href="ley_23_de_1982.jpg"/>
   <file href="memoria.png"/>
   <file href="project-cover.jpg"/>
   <file href="project-thumb.jpg"/>
   <file href="project.json"/>
   <file href="unesco_1-resized.jpg"/>
  </resource>
 </resources>
</manifest>